[{"title":"Sunday","times":{"0":"unsafe","433":"safe","673":"unsafe","1167":"safe","1407":"unsafe"},"safeTimeStrings":[["07:13","11:13"],["19:27","23:27"]]},{"title":"Monday","times":{"0":"unsafe","462":"safe","702":"unsafe","1199":"safe","1439":"unsafe"},"safeTimeStrings":[["07:42","11:42"],["19:59","23:59"]]},{"title":"Tuesday","times":{"0":"unsafe","495":"safe","735":"unsafe","1237":"safe"},"safeTimeStrings":[["08:15","12:15"],["20:37","00:37"]]},{"title":"Wednesday","times":{"0":"safe","37":"unsafe","535":"safe","775":"unsafe","1286":"safe"},"safeTimeStrings":[["08:55","12:55"],["21:26","01:26"]]},{"title":"Thursday","times":{"0":"safe","86":"unsafe","591":"safe","831":"unsafe","1377":"safe"},"safeTimeStrings":[["09:51","13:51"]]},{"title":"Friday","times":{"0":"safe","177":"unsafe","703":"safe","943":"unsafe"},"safeTimeStrings":[["22:57","02:57"],["11:43","15:43"]]},{"title":"Saturday","times":{"0":"unsafe","34":"safe","274":"unsafe","785":"safe","1025":"unsafe"},"safeTimeStrings":[["00:34","04:34"],["13:05","17:05"]]}]
